[
  {
    "info": {
      "symbol": "TRXBTC",
      "orderId": 14488108,
      "clientOrderId": "ilQc21nXZOFCtAMvbnQxbt",
      "price": "0.00000000",
      "origQty": "4618.00000000",
      "executedQty": "4618.00000000",
      "status": "FILLED",
      "timeInForce": "GTC",
      "type": "MARKET",
      "side": "BUY",
      "stopPrice": "0.00000000",
      "icebergQty": "0.00000000",
      "time": 1515371351417,
      "isWorking": true
    },
    "id": "14488108",
    "timestamp": 1515371351417,
    "datetime": "2018-01-08T00:29:11.417Z",
    "symbol": "TRX/BTC",
    "type": "market",
    "side": "buy",
    "price": 0,
    "amount": 4618,
    "cost": 0,
    "filled": 4618,
    "remaining": 0,
    "status": "closed"
  },
  {
    "info": {
      "symbol": "TRXBTC",
      "orderId": 14817381,
      "clientOrderId": "tzuXBh9vY4f4XKSRteHzrz",
      "price": "0.00001100",
      "origQty": "300.00000000",
      "executedQty": "300.00000000",
      "status": "FILLED",
      "timeInForce": "GTC",
      "type": "LIMIT",
      "side": "SELL",
      "stopPrice": "0.00000000",
      "icebergQty": "0.00000000",
      "time": 1515404818261,
      "isWorking": true
    },
    "id": "14817381",
    "timestamp": 1515404818261,
    "datetime": "2018-01-08T09:46:58.261Z",
    "symbol": "TRX/BTC",
    "type": "limit",
    "side": "sell",
    "price": 0.000011,
    "amount": 300,
    "cost": 0.0033,
    "filled": 300,
    "remaining": 0,
    "status": "closed"
  },
  {
    "info": {
      "symbol": "TRXBTC",
      "orderId": 33298832,
      "clientOrderId": "uhp3cTpHPktDWeCjrEcOjR",
      "price": "0.00000405",
      "origQty": "4088.00000000",
      "executedQty": "0.00000000",
      "status": "CANCELED",
      "timeInForce": "GTC",
      "type": "TAKE_PROFIT_LIMIT",
      "side": "SELL",
      "stopPrice": "0.00000405",
      "icebergQty": "0.00000000",
      "time": 1520931385292,
      "isWorking": false
    },
    "id": "33298832",
    "timestamp": 1520931385292,
    "datetime": "2018-03-13T08:56:25.292Z",
    "symbol": "TRX/BTC",
    "type": "take_profit_limit",
    "side": "sell",
    "price": 0.00000405,
    "amount": 4088,
    "cost": 0,
    "filled": 0,
    "remaining": 4088,
    "status": "canceled"
  },
  {
    "info": {
      "symbol": "TRXBTC",
      "orderId": 34232897,
      "clientOrderId": "toto_tata1",
      "transactTime": 1521583675603,
      "price": "0.00000391",
      "origQty": "262.00000000",
      "executedQty": "0.00000000",
      "status": "NEW",
      "timeInForce": "GTC",
      "type": "STOP_LOSS_LIMIT",
      "side": "SELL",
      "stopPrice": "0.00000391"
    },
    "id": "34232897",
    "timestamp": 1521583675603,
    "datetime": "2018-03-20T22:07:55.603Z",
    "symbol": "TRX/BTC",
    "type": "stop_loss_limit",
    "side": "sell",
    "price": 0.00000391,
    "amount": 262,
    "cost": 0,
    "filled": 0,
    "remaining": 262,
    "status": "open"
  }
]

